karaoke/__init__.py
karaoke/main.py
karaoke-0.0.2.dist-info/LICENSE
karaoke-0.0.2.dist-info/METADATA
karaoke-0.0.2.dist-info/WHEEL
karaoke-0.0.2.dist-info/top_level.txt
karaoke-0.0.2.dist-info/RECORD
