Metadata-Version: 2.1
Name: karaoke
Version: 0.0.2
Summary: Karaoke is a lightweight Python library designed to facilitate interactions with song Lyrics.
Author: 0x15BA88FF
Keywords: karaoke,music,lrc
License-File: LICENSE
